README.md
setup.cfg
setup.py
Marshmallow_Arrow.egg-info/PKG-INFO
Marshmallow_Arrow.egg-info/SOURCES.txt
Marshmallow_Arrow.egg-info/dependency_links.txt
Marshmallow_Arrow.egg-info/not-zip-safe
Marshmallow_Arrow.egg-info/requires.txt
Marshmallow_Arrow.egg-info/top_level.txt
marshmallow_arrow/__init__.py