Metadata-Version: 1.1
Name: Marshmallow-Arrow
Version: 1.0
Summary: A Marshmallow Custom Field for Arrow objects.
Home-page: https://github.com/youversion/marshmallow_arrow
Author: Alex Ronoquillo
Author-email: developers@youversion.com
License: MIT
Download-URL: https://github.com/youversion/marshmallow_arrow/archive/master.zip
Keywords: marshmallow,arrow
Platform: any
Classifier: Environment :: Web Environment
Classifier: Intended Audience :: Developers
Classifier: License :: OSI Approved :: MIT License
Classifier: Operating System :: OS Independent
Classifier: Programming Language :: Python
Classifier: Programming Language :: Python :: 3
Classifier: Topic :: Internet :: WWW/HTTP :: Dynamic Content
Classifier: Topic :: Software Development :: Libraries :: Python Modules
